samlauthenticator/__init__.py
samlauthenticator/samlauthenticator.py
tests/test_samlauthenticator.py
jupyterhub_samlauthenticator_kai-0.3.0.dist-info/LICENSE.txt
jupyterhub_samlauthenticator_kai-0.3.0.dist-info/METADATA
jupyterhub_samlauthenticator_kai-0.3.0.dist-info/WHEEL
jupyterhub_samlauthenticator_kai-0.3.0.dist-info/top_level.txt
jupyterhub_samlauthenticator_kai-0.3.0.dist-info/RECORD
