Metadata-Version: 2.1
Name: jupyterhub-samlauthenticator-kai
Version: 0.3.0
Author-email: Hiromasa Ihara <iharahiromasa@gmail.com>
License-File: LICENSE.txt
Requires-Dist: Jinja2 >=2.4
Requires-Dist: jupyterhub >=0.9.0
Requires-Dist: lxml >=4.2.1
Requires-Dist: signxml >=2.6.0
Requires-Dist: pytz >=2019.1
Requires-Dist: pysaml2 >=7.4
Provides-Extra: tests
Requires-Dist: pytest >=4.0.0 ; extra == 'tests'
Requires-Dist: pytest-asyncio >=0.10.0 ; extra == 'tests'
Requires-Dist: pytest-cov >=2.0.0 ; extra == 'tests'
